[{"id":"ecard2-119","name":"Darkness Cube 01","set":"Aquapolis","setId":"ecard2","number":"119","rarity":"Uncommon","types":[],"hp":null,"artist":"\"Big Mama\" Tagawa","imageSmall":"https://images.pokemontcg.io/ecard2/119.png","imageLarge":"https://images.pokemontcg.io/ecard2/119_hires.png"},{"id":"ecard2-121","name":"Fighting Cube 01","set":"Aquapolis","setId":"ecard2","number":"121","rarity":"Uncommon","types":[],"hp":null,"artist":"\"Big Mama\" Tagawa","imageSmall":"https://images.pokemontcg.io/ecard2/121.png","imageLarge":"https://images.pokemontcg.io/ecard2/121_hires.png"},{"id":"ecard2-122","name":"Fire Cube 01","set":"Aquapolis","setId":"ecard2","number":"122","rarity":"Uncommon","types":[],"hp":null,"artist":"\"Big Mama\" Tagawa","imageSmall":"https://images.pokemontcg.io/ecard2/122.png","imageLarge":"https://images.pokemontcg.io/ecard2/122_hires.png"},{"id":"ecard2-124","name":"Grass Cube 01","set":"Aquapolis","setId":"ecard2","number":"124","rarity":"Uncommon","types":[],"hp":null,"artist":"\"Big Mama\" Tagawa","imageSmall":"https://images.pokemontcg.io/ecard2/124.png","imageLarge":"https://images.pokemontcg.io/ecard2/124_hires.png"},{"id":"ecard2-127","name":"Lightning Cube 01","set":"Aquapolis","setId":"ecard2","number":"127","rarity":"Uncommon","types":[],"hp":null,"artist":"\"Big Mama\" Tagawa","imageSmall":"https://images.pokemontcg.io/ecard2/127.png","imageLarge":"https://images.pokemontcg.io/ecard2/127_hires.png"},{"id":"ecard2-129","name":"Metal Cube 01","set":"Aquapolis","setId":"ecard2","number":"129","rarity":"Uncommon","types":[],"hp":null,"artist":"\"Big Mama\" Tagawa","imageSmall":"https://images.pokemontcg.io/ecard2/129.png","imageLarge":"https://images.pokemontcg.io/ecard2/129_hires.png"},{"id":"ecard1-144","name":"Multi Technical Machine 01","set":"Expedition Base Set","setId":"ecard1","number":"144","rarity":"Uncommon","types":[],"hp":null,"artist":"\"Big Mama\" Tagawa","imageSmall":"https://images.pokemontcg.io/ecard1/144.png","imageLarge":"https://images.pokemontcg.io/ecard1/144_hires.png"},{"id":"pop2-9","name":"Multi Technical Machine 01","set":"POP Series 2","setId":"pop2","number":"9","rarity":"Uncommon","types":[],"hp":null,"artist":"\"Big Mama\" Tagawa","imageSmall":"https://images.pokemontcg.io/pop2/9.png","imageLarge":"https://images.pokemontcg.io/pop2/9_hires.png"},{"id":"ecard2-132","name":"Psychic Cube 01","set":"Aquapolis","setId":"ecard2","number":"132","rarity":"Uncommon","types":[],"hp":null,"artist":"\"Big Mama\" Tagawa","imageSmall":"https://images.pokemontcg.io/ecard2/132.png","imageLarge":"https://images.pokemontcg.io/ecard2/132_hires.png"},{"id":"ex4-79","name":"Team Aqua Technical Machine 01","set":"Team Magma vs Team Aqua","setId":"ex4","number":"79","rarity":"Uncommon","types":[],"hp":null,"artist":"Mitsuhiro Arita","imageSmall":"https://images.pokemontcg.io/ex4/79.png","imageLarge":"https://images.pokemontcg.io/ex4/79_hires.png"},{"id":"ex4-84","name":"Team Magma Technical Machine 01","set":"Team Magma vs Team Aqua","setId":"ex4","number":"84","rarity":"Uncommon","types":[],"hp":null,"artist":"Mitsuhiro Arita","imageSmall":"https://images.pokemontcg.io/ex4/84.png","imageLarge":"https://images.pokemontcg.io/ex4/84_hires.png"},{"id":"ecard2-140","name":"Water Cube 01","set":"Aquapolis","setId":"ecard2","number":"140","rarity":"Uncommon","types":[],"hp":null,"artist":"\"Big Mama\" Tagawa","imageSmall":"https://images.pokemontcg.io/ecard2/140.png","imageLarge":"https://images.pokemontcg.io/ecard2/140_hires.png"}]