[{"id":"neo4-10","name":"Dark Typhlosion","set":"Neo Destiny","setId":"neo4","number":"10","rarity":"Rare Holo","types":["Fire"],"hp":"80","artist":"Mitsuhiro Arita","imageSmall":"https://images.pokemontcg.io/neo4/10.png","imageLarge":"https://images.pokemontcg.io/neo4/10_hires.png"},{"id":"ex7-19","name":"Dark Tyranitar","set":"Team Rocket Returns","setId":"ex7","number":"19","rarity":"Rare","types":["Darkness"],"hp":"120","artist":"Nakaoka","imageSmall":"https://images.pokemontcg.io/ex7/19.png","imageLarge":"https://images.pokemontcg.io/ex7/19_hires.png"},{"id":"ex7-20","name":"Dark Tyranitar","set":"Team Rocket Returns","setId":"ex7","number":"20","rarity":"Rare","types":["Fighting","Darkness"],"hp":"120","artist":"Kyoko Koizumi","imageSmall":"https://images.pokemontcg.io/ex7/20.png","imageLarge":"https://images.pokemontcg.io/ex7/20_hires.png"},{"id":"neo4-11","name":"Dark Tyranitar","set":"Neo Destiny","setId":"neo4","number":"11","rarity":"Rare Holo","types":["Fighting"],"hp":"90","artist":"Shin-ichi Yoshida","imageSmall":"https://images.pokemontcg.io/neo4/11.png","imageLarge":"https://images.pokemontcg.io/neo4/11_hires.png"},{"id":"sv10-190","name":"Ethan's Typhlosion","set":"Destined Rivals","setId":"sv10","number":"190","rarity":"Illustration Rare","types":["Fire"],"hp":"170","artist":null,"imageSmall":"https://images.pokemontcg.io/sv10/190.png","imageLarge":"https://images.pokemontcg.io/sv10/190_hires.png"},{"id":"sv10-34","name":"Ethan's Typhlosion","set":"Destined Rivals","setId":"sv10","number":"34","rarity":"Rare","types":["Fire"],"hp":"170","artist":null,"imageSmall":"https://images.pokemontcg.io/sv10/34.png","imageLarge":"https://images.pokemontcg.io/sv10/34_hires.png"},{"id":"swsh10-52","name":"Hisuian Typhlosion","set":"Astral Radiance","setId":"swsh10","number":"52","rarity":"Rare Holo","types":["Psychic"],"hp":"150","artist":"Kouki Saitou","imageSmall":"https://images.pokemontcg.io/swsh10/52.png","imageLarge":"https://images.pokemontcg.io/swsh10/52_hires.png"},{"id":"swsh10-169","name":"Hisuian Typhlosion V","set":"Astral Radiance","setId":"swsh10","number":"169","rarity":"Rare Ultra","types":["Psychic"],"hp":"210","artist":"5ban Graphics","imageSmall":"https://images.pokemontcg.io/swsh10/169.png","imageLarge":"https://images.pokemontcg.io/swsh10/169_hires.png"},{"id":"swsh10-53","name":"Hisuian Typhlosion V","set":"Astral Radiance","setId":"swsh10","number":"53","rarity":"Rare Holo V","types":["Psychic"],"hp":"210","artist":"Shin Nagasawa","imageSmall":"https://images.pokemontcg.io/swsh10/53.png","imageLarge":"https://images.pokemontcg.io/swsh10/53_hires.png"},{"id":"swshp-SWSH237","name":"Hisuian Typhlosion V","set":"SWSH Black Star Promos","setId":"swshp","number":"SWSH237","rarity":"Promo","types":["Psychic"],"hp":"210","artist":"5ban Graphics","imageSmall":"https://images.pokemontcg.io/swshp/SWSH237.png","imageLarge":"https://images.pokemontcg.io/swshp/SWSH237_hires.png"},{"id":"swsh10-193","name":"Hisuian Typhlosion VSTAR","set":"Astral Radiance","setId":"swsh10","number":"193","rarity":"Rare Rainbow","types":["Psychic"],"hp":"260","artist":"5ban Graphics","imageSmall":"https://images.pokemontcg.io/swsh10/193.png","imageLarge":"https://images.pokemontcg.io/swsh10/193_hires.png"},{"id":"swsh10-54","name":"Hisuian Typhlosion VSTAR","set":"Astral Radiance","setId":"swsh10","number":"54","rarity":"Rare Holo VSTAR","types":["Psychic"],"hp":"260","artist":"5ban Graphics","imageSmall":"https://images.pokemontcg.io/swsh10/54.png","imageLarge":"https://images.pokemontcg.io/swsh10/54_hires.png"},{"id":"xy7-43","name":"M Tyranitar-EX","set":"Ancient Origins","setId":"xy7","number":"43","rarity":"Rare Holo EX","types":["Darkness"],"hp":"240","artist":"5ban Graphics","imageSmall":"https://images.pokemontcg.io/xy7/43.png","imageLarge":"https://images.pokemontcg.io/xy7/43_hires.png"},{"id":"xy7-92","name":"M Tyranitar-EX","set":"Ancient Origins","setId":"xy7","number":"92","rarity":"Rare Ultra","types":["Darkness"],"hp":"240","artist":"5ban Graphics","imageSmall":"https://images.pokemontcg.io/xy7/92.png","imageLarge":"https://images.pokemontcg.io/xy7/92_hires.png"},{"id":"sm11-126","name":"Mega Sableye & Tyranitar-GX","set":"Unified Minds","setId":"sm11","number":"126","rarity":"Rare Holo GX","types":["Darkness"],"hp":"280","artist":"Mitsuhiro Arita","imageSmall":"https://images.pokemontcg.io/sm11/126.png","imageLarge":"https://images.pokemontcg.io/sm11/126_hires.png"},{"id":"sm11-225","name":"Mega Sableye & Tyranitar-GX","set":"Unified Minds","setId":"sm11","number":"225","rarity":"Rare Ultra","types":["Darkness"],"hp":"280","artist":"5ban Graphics","imageSmall":"https://images.pokemontcg.io/sm11/225.png","imageLarge":"https://images.pokemontcg.io/sm11/225_hires.png"},{"id":"sm11-226","name":"Mega Sableye & Tyranitar-GX","set":"Unified Minds","setId":"sm11","number":"226","rarity":"Rare Ultra","types":["Darkness"],"hp":"280","artist":"chibi","imageSmall":"https://images.pokemontcg.io/sm11/226.png","imageLarge":"https://images.pokemontcg.io/sm11/226_hires.png"},{"id":"sm11-245","name":"Mega Sableye & Tyranitar-GX","set":"Unified Minds","setId":"sm11","number":"245","rarity":"Rare Rainbow","types":["Darkness"],"hp":"280","artist":"5ban Graphics","imageSmall":"https://images.pokemontcg.io/sm11/245.png","imageLarge":"https://images.pokemontcg.io/sm11/245_hires.png"},{"id":"neo4-113","name":"Shining Tyranitar","set":"Neo Destiny","setId":"neo4","number":"113","rarity":"Rare Shining","types":["Darkness"],"hp":"80","artist":"Ken Sugimori","imageSmall":"https://images.pokemontcg.io/neo4/113.png","imageLarge":"https://images.pokemontcg.io/neo4/113_hires.png"},{"id":"sv10-96","name":"Team Rocket's Tyranitar","set":"Destined Rivals","setId":"sv10","number":"96","rarity":"Rare","types":["Fighting"],"hp":"180","artist":null,"imageSmall":"https://images.pokemontcg.io/sv10/96.png","imageLarge":"https://images.pokemontcg.io/sv10/96_hires.png"},{"id":"sv8-190","name":"Tyme","set":"Surging Sparks","setId":"sv8","number":"190","rarity":"Uncommon","types":[],"hp":null,"artist":null,"imageSmall":"https://images.pokemontcg.io/sv8/190.png","imageLarge":"https://images.pokemontcg.io/sv8/190_hires.png"},{"id":"sv8pt5-143","name":"Tyme","set":"Prismatic Evolutions","setId":"sv8pt5","number":"143","rarity":"Ultra Rare","types":[],"hp":null,"artist":null,"imageSmall":"https://images.pokemontcg.io/sv8pt5/143.png","imageLarge":"https://images.pokemontcg.io/sv8pt5/143_hires.png"},{"id":"bw11-40","name":"Tympole","set":"Legendary Treasures","setId":"bw11","number":"40","rarity":"Common","types":["Water"],"hp":"60","artist":"Kyoko Umemoto","imageSmall":"https://images.pokemontcg.io/bw11/40.png","imageLarge":"https://images.pokemontcg.io/bw11/40_hires.png"},{"id":"bw3-22","name":"Tympole","set":"Noble Victories","setId":"bw3","number":"22","rarity":"Common","types":["Water"],"hp":"60","artist":"Atsuko Nishida","imageSmall":"https://images.pokemontcg.io/bw3/22.png","imageLarge":"https://images.pokemontcg.io/bw3/22_hires.png"},{"id":"bw5-31","name":"Tympole","set":"Dark Explorers","setId":"bw5","number":"31","rarity":"Common","types":["Water"],"hp":"60","artist":"Kouki Saitou","imageSmall":"https://images.pokemontcg.io/bw5/31.png","imageLarge":"https://images.pokemontcg.io/bw5/31_hires.png"},{"id":"bw6-34","name":"Tympole","set":"Dragons Exalted","setId":"bw6","number":"34","rarity":"Common","types":["Water"],"hp":"50","artist":"Midori Harada","imageSmall":"https://images.pokemontcg.io/bw6/34.png","imageLarge":"https://images.pokemontcg.io/bw6/34_hires.png"},{"id":"bw9-24","name":"Tympole","set":"Plasma Freeze","setId":"bw9","number":"24","rarity":"Common","types":["Water"],"hp":"60","artist":"MAHOU","imageSmall":"https://images.pokemontcg.io/bw9/24.png","imageLarge":"https://images.pokemontcg.io/bw9/24_hires.png"},{"id":"sm12-58","name":"Tympole","set":"Cosmic Eclipse","setId":"sm12","number":"58","rarity":"Common","types":["Water"],"hp":"60","artist":"Asako Ito","imageSmall":"https://images.pokemontcg.io/sm12/58.png","imageLarge":"https://images.pokemontcg.io/sm12/58_hires.png"},{"id":"sv3-50","name":"Tympole","set":"Obsidian Flames","setId":"sv3","number":"50","rarity":"Common","types":["Water"],"hp":"70","artist":"OKUBO","imageSmall":"https://images.pokemontcg.io/sv3/50.png","imageLarge":"https://images.pokemontcg.io/sv3/50_hires.png"},{"id":"swsh2-44","name":"Tympole","set":"Rebel Clash","setId":"swsh2","number":"44","rarity":"Common","types":["Water"],"hp":"60","artist":"Aya Kusube","imageSmall":"https://images.pokemontcg.io/swsh2/44.png","imageLarge":"https://images.pokemontcg.io/swsh2/44_hires.png"},{"id":"swsh7-42","name":"Tympole","set":"Evolving Skies","setId":"swsh7","number":"42","rarity":"Common","types":["Water"],"hp":"70","artist":"Mina Nakai","imageSmall":"https://images.pokemontcg.io/swsh7/42.png","imageLarge":"https://images.pokemontcg.io/swsh7/42_hires.png"},{"id":"xy9-33","name":"Tympole","set":"BREAKpoint","setId":"xy9","number":"33","rarity":"Common","types":["Water"],"hp":"60","artist":"Miki Tanaka","imageSmall":"https://images.pokemontcg.io/xy9/33.png","imageLarge":"https://images.pokemontcg.io/xy9/33_hires.png"},{"id":"zsv10pt5-103","name":"Tympole","set":"Black Bolt","setId":"zsv10pt5","number":"103","rarity":"Illustration Rare","types":["Water"],"hp":"60","artist":"aspara","imageSmall":"https://images.pokemontcg.io/zsv10pt5/103.png","imageLarge":"https://images.pokemontcg.io/zsv10pt5/103_hires.png"},{"id":"zsv10pt5-19","name":"Tympole","set":"Black Bolt","setId":"zsv10pt5","number":"19","rarity":"Common","types":["Water"],"hp":"60","artist":"Yukihiro Tada","imageSmall":"https://images.pokemontcg.io/zsv10pt5/19.png","imageLarge":"https://images.pokemontcg.io/zsv10pt5/19_hires.png"},{"id":"bw10-31","name":"Tynamo","set":"Plasma Blast","setId":"bw10","number":"31","rarity":"Common","types":["Lightning"],"hp":"30","artist":"Shigenori Negishi","imageSmall":"https://images.pokemontcg.io/bw10/31.png","imageLarge":"https://images.pokemontcg.io/bw10/31_hires.png"},{"id":"bw3-38","name":"Tynamo","set":"Noble Victories","setId":"bw3","number":"38","rarity":"Common","types":["Lightning"],"hp":"40","artist":"sui","imageSmall":"https://images.pokemontcg.io/bw3/38.png","imageLarge":"https://images.pokemontcg.io/bw3/38_hires.png"},{"id":"bw3-39","name":"Tynamo","set":"Noble Victories","setId":"bw3","number":"39","rarity":"Common","types":["Lightning"],"hp":"30","artist":"Naoki Saito","imageSmall":"https://images.pokemontcg.io/bw3/39.png","imageLarge":"https://images.pokemontcg.io/bw3/39_hires.png"},{"id":"bw5-44","name":"Tynamo","set":"Dark Explorers","setId":"bw5","number":"44","rarity":"Common","types":["Lightning"],"hp":"40","artist":"Midori Harada","imageSmall":"https://images.pokemontcg.io/bw5/44.png","imageLarge":"https://images.pokemontcg.io/bw5/44_hires.png"},{"id":"bw5-45","name":"Tynamo","set":"Dark Explorers","setId":"bw5","number":"45","rarity":"Common","types":["Lightning"],"hp":"40","artist":"Akira Komayama","imageSmall":"https://images.pokemontcg.io/bw5/45.png","imageLarge":"https://images.pokemontcg.io/bw5/45_hires.png"},{"id":"mcd22-10","name":"Tynamo","set":"McDonald's Collection 2022","setId":"mcd22","number":"10","rarity":null,"types":["Lightning"],"hp":"40","artist":"sowsow","imageSmall":"https://images.pokemontcg.io/mcd22/10.png","imageLarge":"https://images.pokemontcg.io/mcd22/10_hires.png"},{"id":"me2pt5-59","name":"Tynamo","set":"Ascended Heroes","setId":"me2pt5","number":"59","rarity":"Common","types":["Lightning"],"hp":"40","artist":"Jerky","imageSmall":"https://images.scrydex.com/pokemon/me2pt5-59/small","imageLarge":"https://images.scrydex.com/pokemon/me2pt5-59/large"},{"id":"sm11-63","name":"Tynamo","set":"Unified Minds","setId":"sm11","number":"63","rarity":"Common","types":["Lightning"],"hp":"30","artist":"Mina Nakai","imageSmall":"https://images.pokemontcg.io/sm11/63.png","imageLarge":"https://images.pokemontcg.io/sm11/63_hires.png"},{"id":"sm11-64","name":"Tynamo","set":"Unified Minds","setId":"sm11","number":"64","rarity":"Common","types":["Lightning"],"hp":"40","artist":"SATOSHI NAKAI","imageSmall":"https://images.pokemontcg.io/sm11/64.png","imageLarge":"https://images.pokemontcg.io/sm11/64_hires.png"},{"id":"sm3-44","name":"Tynamo","set":"Burning Shadows","setId":"sm3","number":"44","rarity":"Common","types":["Lightning"],"hp":"40","artist":"Asako Ito","imageSmall":"https://images.pokemontcg.io/sm3/44.png","imageLarge":"https://images.pokemontcg.io/sm3/44_hires.png"},{"id":"sv3-67","name":"Tynamo","set":"Obsidian Flames","setId":"sv3","number":"67","rarity":"Common","types":["Lightning"],"hp":"40","artist":"Kagemaru Himeno","imageSmall":"https://images.pokemontcg.io/sv3/67.png","imageLarge":"https://images.pokemontcg.io/sv3/67_hires.png"},{"id":"swsh11-59","name":"Tynamo","set":"Lost Origin","setId":"swsh11","number":"59","rarity":"Common","types":["Lightning"],"hp":"30","artist":"Yukiko Baba","imageSmall":"https://images.pokemontcg.io/swsh11/59.png","imageLarge":"https://images.pokemontcg.io/swsh11/59_hires.png"},{"id":"swsh4-57","name":"Tynamo","set":"Vivid Voltage","setId":"swsh4","number":"57","rarity":"Common","types":["Lightning"],"hp":"40","artist":"sowsow","imageSmall":"https://images.pokemontcg.io/swsh4/57.png","imageLarge":"https://images.pokemontcg.io/swsh4/57_hires.png"},{"id":"swsh8-95","name":"Tynamo","set":"Fusion Strike","setId":"swsh8","number":"95","rarity":"Common","types":["Lightning"],"hp":"40","artist":"Yuka Morii","imageSmall":"https://images.pokemontcg.io/swsh8/95.png","imageLarge":"https://images.pokemontcg.io/swsh8/95_hires.png"},{"id":"xy5-62","name":"Tynamo","set":"Primal Clash","setId":"xy5","number":"62","rarity":"Common","types":["Lightning"],"hp":"40","artist":"Atsuko Nishida","imageSmall":"https://images.pokemontcg.io/xy5/62.png","imageLarge":"https://images.pokemontcg.io/xy5/62_hires.png"},{"id":"zsv10pt5-113","name":"Tynamo","set":"Black Bolt","setId":"zsv10pt5","number":"113","rarity":"Illustration Rare","types":["Lightning"],"hp":"40","artist":"ryoma uratsuka","imageSmall":"https://images.pokemontcg.io/zsv10pt5/113.png","imageLarge":"https://images.pokemontcg.io/zsv10pt5/113_hires.png"},{"id":"zsv10pt5-30","name":"Tynamo","set":"Black Bolt","setId":"zsv10pt5","number":"30","rarity":"Common","types":["Lightning"],"hp":"40","artist":"Jerky","imageSmall":"https://images.pokemontcg.io/zsv10pt5/30.png","imageLarge":"https://images.pokemontcg.io/zsv10pt5/30_hires.png"},{"id":"sm11-183","name":"Type: Null","set":"Unified Minds","setId":"sm11","number":"183","rarity":"Uncommon","types":["Colorless"],"hp":"100","artist":"tetsuya koizumi","imageSmall":"https://images.pokemontcg.io/sm11/183.png","imageLarge":"https://images.pokemontcg.io/sm11/183_hires.png"},{"id":"sm12-183","name":"Type: Null","set":"Cosmic Eclipse","setId":"sm12","number":"183","rarity":"Uncommon","types":["Colorless"],"hp":"110","artist":"KEIICHIRO ITO","imageSmall":"https://images.pokemontcg.io/sm12/183.png","imageLarge":"https://images.pokemontcg.io/sm12/183_hires.png"},{"id":"sm4-89","name":"Type: Null","set":"Crimson Invasion","setId":"sm4","number":"89","rarity":"Rare Holo","types":["Colorless"],"hp":"110","artist":"Hitoshi Ariga","imageSmall":"https://images.pokemontcg.io/sm4/89.png","imageLarge":"https://images.pokemontcg.io/sm4/89_hires.png"},{"id":"sm5-115","name":"Type: Null","set":"Ultra Prism","setId":"sm5","number":"115","rarity":"Rare","types":["Colorless"],"hp":"110","artist":"match","imageSmall":"https://images.pokemontcg.io/sm5/115.png","imageLarge":"https://images.pokemontcg.io/sm5/115_hires.png"},{"id":"sma-SV45","name":"Type: Null","set":"Hidden Fates Shiny Vault","setId":"sma","number":"SV45","rarity":"Rare Shiny","types":["Colorless"],"hp":"110","artist":"Shin Nagasawa","imageSmall":"https://images.pokemontcg.io/sma/SV45.png","imageLarge":"https://images.pokemontcg.io/sma/SV45_hires.png"},{"id":"col1-35","name":"Typhlosion","set":"Call of Legends","setId":"col1","number":"35","rarity":"Rare","types":["Fire"],"hp":"130","artist":"Kagemaru Himeno","imageSmall":"https://images.pokemontcg.io/col1/35.png","imageLarge":"https://images.pokemontcg.io/col1/35_hires.png"},{"id":"dp2-16","name":"Typhlosion","set":"Mysterious Treasures","setId":"dp2","number":"16","rarity":"Rare Holo","types":["Fire"],"hp":"110","artist":"Kazuyuki Kano","imageSmall":"https://images.pokemontcg.io/dp2/16.png","imageLarge":"https://images.pokemontcg.io/dp2/16_hires.png"},{"id":"ecard1-28","name":"Typhlosion","set":"Expedition Base Set","setId":"ecard1","number":"28","rarity":"Rare Holo","types":["Fire"],"hp":"100","artist":"K. Hoshiba","imageSmall":"https://images.pokemontcg.io/ecard1/28.png","imageLarge":"https://images.pokemontcg.io/ecard1/28_hires.png"},{"id":"ecard1-64","name":"Typhlosion","set":"Expedition Base Set","setId":"ecard1","number":"64","rarity":"Rare","types":["Fire"],"hp":"100","artist":"Hiroaki Ito","imageSmall":"https://images.pokemontcg.io/ecard1/64.png","imageLarge":"https://images.pokemontcg.io/ecard1/64_hires.png"},{"id":"ecard1-65","name":"Typhlosion","set":"Expedition Base Set","setId":"ecard1","number":"65","rarity":"Rare","types":["Fire"],"hp":"100","artist":"K. Hoshiba","imageSmall":"https://images.pokemontcg.io/ecard1/65.png","imageLarge":"https://images.pokemontcg.io/ecard1/65_hires.png"},{"id":"ex10-17","name":"Typhlosion","set":"Unseen Forces","setId":"ex10","number":"17","rarity":"Rare Holo","types":["Fire"],"hp":"110","artist":"Hajime Kusajima","imageSmall":"https://images.pokemontcg.io/ex10/17.png","imageLarge":"https://images.pokemontcg.io/ex10/17_hires.png"},{"id":"hgss1-110","name":"Typhlosion","set":"HeartGold & SoulSilver","setId":"hgss1","number":"110","rarity":"Rare Prime","types":["Fire"],"hp":"140","artist":"Wataru Kawahara","imageSmall":"https://images.pokemontcg.io/hgss1/110.png","imageLarge":"https://images.pokemontcg.io/hgss1/110_hires.png"},{"id":"hgss1-32","name":"Typhlosion","set":"HeartGold & SoulSilver","setId":"hgss1","number":"32","rarity":"Rare","types":["Fire"],"hp":"130","artist":"Kagemaru Himeno","imageSmall":"https://images.pokemontcg.io/hgss1/32.png","imageLarge":"https://images.pokemontcg.io/hgss1/32_hires.png"},{"id":"hsp-HGSS09","name":"Typhlosion","set":"HGSS Black Star Promos","setId":"hsp","number":"HGSS09","rarity":"Promo","types":["Fire"],"hp":"140","artist":"Wataru Kawahara","imageSmall":"https://images.pokemontcg.io/hsp/HGSS09.png","imageLarge":"https://images.pokemontcg.io/hsp/HGSS09_hires.png"},{"id":"neo1-17","name":"Typhlosion","set":"Neo Genesis","setId":"neo1","number":"17","rarity":"Rare Holo","types":["Fire"],"hp":"100","artist":"Shin-ichi Yoshida","imageSmall":"https://images.pokemontcg.io/neo1/17.png","imageLarge":"https://images.pokemontcg.io/neo1/17_hires.png"},{"id":"neo1-18","name":"Typhlosion","set":"Neo Genesis","setId":"neo1","number":"18","rarity":"Rare Holo","types":["Fire"],"hp":"100","artist":"Ken Sugimori","imageSmall":"https://images.pokemontcg.io/neo1/18.png","imageLarge":"https://images.pokemontcg.io/neo1/18_hires.png"},{"id":"np-34","name":"Typhlosion","set":"Nintendo Black Star Promos","setId":"np","number":"34","rarity":"Promo","types":["Fire"],"hp":"110","artist":"Hajime Kusajima","imageSmall":"https://images.pokemontcg.io/np/34.png","imageLarge":"https://images.pokemontcg.io/np/34_hires.png"},{"id":"sm8-42","name":"Typhlosion","set":"Lost Thunder","setId":"sm8","number":"42","rarity":"Rare Holo","types":["Fire"],"hp":"160","artist":"Kouki Saitou","imageSmall":"https://images.pokemontcg.io/sm8/42.png","imageLarge":"https://images.pokemontcg.io/sm8/42_hires.png"},{"id":"smp-SM185","name":"Typhlosion","set":"SM Black Star Promos","setId":"smp","number":"SM185","rarity":"Promo","types":["Fire"],"hp":"150","artist":"Hideki Ishikawa","imageSmall":"https://images.pokemontcg.io/smp/SM185.png","imageLarge":"https://images.pokemontcg.io/smp/SM185_hires.png"},{"id":"xy8-20","name":"Typhlosion","set":"BREAKthrough","setId":"xy8","number":"20","rarity":"Rare Holo","types":["Fire"],"hp":"150","artist":"Megumi Mizutani","imageSmall":"https://images.pokemontcg.io/xy8/20.png","imageLarge":"https://images.pokemontcg.io/xy8/20_hires.png"},{"id":"ex10-110","name":"Typhlosion ex","set":"Unseen Forces","setId":"ex10","number":"110","rarity":"Rare Holo EX","types":["Fire"],"hp":"150","artist":"Mitsuhiro Arita","imageSmall":"https://images.pokemontcg.io/ex10/110.png","imageLarge":"https://images.pokemontcg.io/ex10/110_hires.png"},{"id":"ex2-99","name":"Typhlosion ex","set":"Sandstorm","setId":"ex2","number":"99","rarity":"Rare Holo EX","types":["Fire"],"hp":"160","artist":"Hikaru Koike","imageSmall":"https://images.pokemontcg.io/ex2/99.png","imageLarge":"https://images.pokemontcg.io/ex2/99_hires.png"},{"id":"ex15-12","name":"Typhlosion δ","set":"Dragon Frontiers","setId":"ex15","number":"12","rarity":"Rare Holo","types":["Psychic"],"hp":"100","artist":"Hisao Nakamura","imageSmall":"https://images.pokemontcg.io/ex15/12.png","imageLarge":"https://images.pokemontcg.io/ex15/12_hires.png"},{"id":"dp2-17","name":"Tyranitar","set":"Mysterious Treasures","setId":"dp2","number":"17","rarity":"Rare Holo","types":["Darkness"],"hp":"140","artist":"Masakazu Fukuda","imageSmall":"https://images.pokemontcg.io/dp2/17.png","imageLarge":"https://images.pokemontcg.io/dp2/17_hires.png"},{"id":"dp7-30","name":"Tyranitar","set":"Stormfront","setId":"dp7","number":"30","rarity":"Rare","types":["Darkness"],"hp":"140","artist":"Kagemaru Himeno","imageSmall":"https://images.pokemontcg.io/dp7/30.png","imageLarge":"https://images.pokemontcg.io/dp7/30_hires.png"},{"id":"ecard1-29","name":"Tyranitar","set":"Expedition Base Set","setId":"ecard1","number":"29","rarity":"Rare Holo","types":["Darkness"],"hp":"120","artist":"Kimiya Masago","imageSmall":"https://images.pokemontcg.io/ecard1/29.png","imageLarge":"https://images.pokemontcg.io/ecard1/29_hires.png"},{"id":"ecard1-66","name":"Tyranitar","set":"Expedition Base Set","setId":"ecard1","number":"66","rarity":"Rare","types":["Darkness"],"hp":"120","artist":"Kimiya Masago","imageSmall":"https://images.pokemontcg.io/ecard1/66.png","imageLarge":"https://images.pokemontcg.io/ecard1/66_hires.png"},{"id":"ecard2-40","name":"Tyranitar","set":"Aquapolis","setId":"ecard2","number":"40","rarity":"Rare","types":["Darkness"],"hp":"120","artist":"Naoyo Kimura","imageSmall":"https://images.pokemontcg.io/ecard2/40.png","imageLarge":"https://images.pokemontcg.io/ecard2/40_hires.png"},{"id":"ecard2-H28","name":"Tyranitar","set":"Aquapolis","setId":"ecard2","number":"H28","rarity":"Rare Holo","types":["Darkness"],"hp":"120","artist":"Naoyo Kimura","imageSmall":"https://images.pokemontcg.io/ecard2/H28.png","imageLarge":"https://images.pokemontcg.io/ecard2/H28_hires.png"},{"id":"hgss2-26","name":"Tyranitar","set":"HS—Unleashed","setId":"hgss2","number":"26","rarity":"Rare","types":["Darkness"],"hp":"140","artist":"Kouki Saitou","imageSmall":"https://images.pokemontcg.io/hgss2/26.png","imageLarge":"https://images.pokemontcg.io/hgss2/26_hires.png"},{"id":"hgss2-88","name":"Tyranitar","set":"HS—Unleashed","setId":"hgss2","number":"88","rarity":"Rare Prime","types":["Darkness"],"hp":"160","artist":"Wataru Kawahara","imageSmall":"https://images.pokemontcg.io/hgss2/88.png","imageLarge":"https://images.pokemontcg.io/hgss2/88_hires.png"},{"id":"neo2-12","name":"Tyranitar","set":"Neo Discovery","setId":"neo2","number":"12","rarity":"Rare Holo","types":["Darkness"],"hp":"100","artist":"Hironobu Yoshida","imageSmall":"https://images.pokemontcg.io/neo2/12.png","imageLarge":"https://images.pokemontcg.io/neo2/12_hires.png"},{"id":"neo2-31","name":"Tyranitar","set":"Neo Discovery","setId":"neo2","number":"31","rarity":"Rare","types":["Darkness"],"hp":"100","artist":"Hironobu Yoshida","imageSmall":"https://images.pokemontcg.io/neo2/31.png","imageLarge":"https://images.pokemontcg.io/neo2/31_hires.png"},{"id":"pgo-43","name":"Tyranitar","set":"Pokémon GO","setId":"pgo","number":"43","rarity":"Rare Holo","types":["Darkness"],"hp":"180","artist":"Nisota Niso","imageSmall":"https://images.pokemontcg.io/pgo/43.png","imageLarge":"https://images.pokemontcg.io/pgo/43_hires.png"},{"id":"sm7-87","name":"Tyranitar","set":"Celestial Storm","setId":"sm7","number":"87","rarity":"Rare Holo","types":["Darkness"],"hp":"170","artist":"Hironobu Yoshida","imageSmall":"https://images.pokemontcg.io/sm7/87.png","imageLarge":"https://images.pokemontcg.io/sm7/87_hires.png"},{"id":"sm9-85","name":"Tyranitar","set":"Team Up","setId":"sm9","number":"85","rarity":"Rare Holo","types":["Darkness"],"hp":"170","artist":"Hasuno","imageSmall":"https://images.pokemontcg.io/sm9/85.png","imageLarge":"https://images.pokemontcg.io/sm9/85_hires.png"},{"id":"sv2-135","name":"Tyranitar","set":"Paldea Evolved","setId":"sv2","number":"135","rarity":"Rare","types":["Darkness"],"hp":"180","artist":"hncl","imageSmall":"https://images.pokemontcg.io/sv2/135.png","imageLarge":"https://images.pokemontcg.io/sv2/135_hires.png"},{"id":"sv2-222","name":"Tyranitar","set":"Paldea Evolved","setId":"sv2","number":"222","rarity":"Illustration Rare","types":["Darkness"],"hp":"180","artist":"Nurikabe","imageSmall":"https://images.pokemontcg.io/sv2/222.png","imageLarge":"https://images.pokemontcg.io/sv2/222_hires.png"},{"id":"sv9-95","name":"Tyranitar","set":"Journey Together","setId":"sv9","number":"95","rarity":"Rare","types":["Darkness"],"hp":"190","artist":null,"imageSmall":"https://images.pokemontcg.io/sv9/95.png","imageLarge":"https://images.pokemontcg.io/sv9/95_hires.png"},{"id":"swsh3-88","name":"Tyranitar","set":"Darkness Ablaze","setId":"swsh3","number":"88","rarity":"Rare Holo","types":["Fighting"],"hp":"180","artist":"nagimiso","imageSmall":"https://images.pokemontcg.io/swsh3/88.png","imageLarge":"https://images.pokemontcg.io/swsh3/88_hires.png"},{"id":"xy10-56","name":"Tyranitar","set":"Fates Collide","setId":"xy10","number":"56","rarity":"Rare Holo","types":["Darkness"],"hp":"160","artist":"Satoshi Shirai","imageSmall":"https://images.pokemontcg.io/xy10/56.png","imageLarge":"https://images.pokemontcg.io/xy10/56_hires.png"},{"id":"xyp-XY130","name":"Tyranitar","set":"XY Black Star Promos","setId":"xyp","number":"XY130","rarity":"Promo","types":["Darkness"],"hp":"160","artist":"Satoshi Shirai","imageSmall":"https://images.pokemontcg.io/xyp/XY130.png","imageLarge":"https://images.pokemontcg.io/xyp/XY130_hires.png"},{"id":"ex10-111","name":"Tyranitar ex","set":"Unseen Forces","setId":"ex10","number":"111","rarity":"Rare Holo EX","types":["Darkness"],"hp":"160","artist":"Mitsuhiro Arita","imageSmall":"https://images.pokemontcg.io/ex10/111.png","imageLarge":"https://images.pokemontcg.io/ex10/111_hires.png"},{"id":"pop1-17","name":"Tyranitar ex","set":"POP Series 1","setId":"pop1","number":"17","rarity":"Rare","types":["Darkness"],"hp":"150","artist":"Hisao Nakamura","imageSmall":"https://images.pokemontcg.io/pop1/17.png","imageLarge":"https://images.pokemontcg.io/pop1/17_hires.png"},{"id":"sv3-211","name":"Tyranitar ex","set":"Obsidian Flames","setId":"sv3","number":"211","rarity":"Ultra Rare","types":["Lightning"],"hp":"340","artist":"5ban Graphics","imageSmall":"https://images.pokemontcg.io/sv3/211.png","imageLarge":"https://images.pokemontcg.io/sv3/211_hires.png"},{"id":"sv3-66","name":"Tyranitar ex","set":"Obsidian Flames","setId":"sv3","number":"66","rarity":"Double Rare","types":["Lightning"],"hp":"340","artist":"5ban Graphics","imageSmall":"https://images.pokemontcg.io/sv3/66.png","imageLarge":"https://images.pokemontcg.io/sv3/66_hires.png"},{"id":"sv8pt5-64","name":"Tyranitar ex","set":"Prismatic Evolutions","setId":"sv8pt5","number":"64","rarity":"Double Rare","types":["Darkness"],"hp":"340","artist":null,"imageSmall":"https://images.pokemontcg.io/sv8pt5/64.png","imageLarge":"https://images.pokemontcg.io/sv8pt5/64_hires.png"},{"id":"ex15-99","name":"Tyranitar ex δ","set":"Dragon Frontiers","setId":"ex15","number":"99","rarity":"Rare Holo EX","types":["Lightning"],"hp":"150","artist":"Yusuke Shimada","imageSmall":"https://images.pokemontcg.io/ex15/99.png","imageLarge":"https://images.pokemontcg.io/ex15/99_hires.png"},{"id":"xy7-81","name":"Tyranitar Spirit Link","set":"Ancient Origins","setId":"xy7","number":"81","rarity":"Uncommon","types":[],"hp":null,"artist":"5ban Graphics","imageSmall":"https://images.pokemontcg.io/xy7/81.png","imageLarge":"https://images.pokemontcg.io/xy7/81_hires.png"},{"id":"swsh5-154","name":"Tyranitar V","set":"Battle Styles","setId":"swsh5","number":"154","rarity":"Rare Ultra","types":["Darkness"],"hp":"230","artist":"Ayaka Yoshida","imageSmall":"https://images.pokemontcg.io/swsh5/154.png","imageLarge":"https://images.pokemontcg.io/swsh5/154_hires.png"},{"id":"swsh5-155","name":"Tyranitar V","set":"Battle Styles","setId":"swsh5","number":"155","rarity":"Rare Ultra","types":["Darkness"],"hp":"230","artist":"HYOGONOSUKE","imageSmall":"https://images.pokemontcg.io/swsh5/155.png","imageLarge":"https://images.pokemontcg.io/swsh5/155_hires.png"},{"id":"swsh5-97","name":"Tyranitar V","set":"Battle Styles","setId":"swsh5","number":"97","rarity":"Rare Holo V","types":["Darkness"],"hp":"230","artist":"Ayaka Yoshida","imageSmall":"https://images.pokemontcg.io/swsh5/97.png","imageLarge":"https://images.pokemontcg.io/swsh5/97_hires.png"},{"id":"swsh8-158","name":"Tyranitar V","set":"Fusion Strike","setId":"swsh8","number":"158","rarity":"Rare Holo V","types":["Darkness"],"hp":"230","artist":"5ban Graphics","imageSmall":"https://images.pokemontcg.io/swsh8/158.png","imageLarge":"https://images.pokemontcg.io/swsh8/158_hires.png"},{"id":"swshp-SWSH109","name":"Tyranitar V","set":"SWSH Black Star Promos","setId":"swshp","number":"SWSH109","rarity":"Promo","types":["Darkness"],"hp":"230","artist":"PLANETA Tsuji","imageSmall":"https://images.pokemontcg.io/swshp/SWSH109.png","imageLarge":"https://images.pokemontcg.io/swshp/SWSH109_hires.png"},{"id":"ex11-16","name":"Tyranitar δ","set":"Delta Species","setId":"ex11","number":"16","rarity":"Rare Holo","types":["Fire","Metal"],"hp":"120","artist":"Mitsuhiro Arita","imageSmall":"https://images.pokemontcg.io/ex11/16.png","imageLarge":"https://images.pokemontcg.io/ex11/16_hires.png"},{"id":"xy7-42","name":"Tyranitar-EX","set":"Ancient Origins","setId":"xy7","number":"42","rarity":"Rare Holo EX","types":["Darkness"],"hp":"180","artist":"Eske Yoshinob","imageSmall":"https://images.pokemontcg.io/xy7/42.png","imageLarge":"https://images.pokemontcg.io/xy7/42_hires.png"},{"id":"xy7-91","name":"Tyranitar-EX","set":"Ancient Origins","setId":"xy7","number":"91","rarity":"Rare Ultra","types":["Darkness"],"hp":"180","artist":"Ryo Ueda","imageSmall":"https://images.pokemontcg.io/xy7/91.png","imageLarge":"https://images.pokemontcg.io/xy7/91_hires.png"},{"id":"sm8-121","name":"Tyranitar-GX","set":"Lost Thunder","setId":"sm8","number":"121","rarity":"Rare Holo GX","types":["Darkness"],"hp":"250","artist":"5ban Graphics","imageSmall":"https://images.pokemontcg.io/sm8/121.png","imageLarge":"https://images.pokemontcg.io/sm8/121_hires.png"},{"id":"sm8-203","name":"Tyranitar-GX","set":"Lost Thunder","setId":"sm8","number":"203","rarity":"Rare Ultra","types":["Darkness"],"hp":"250","artist":"5ban Graphics","imageSmall":"https://images.pokemontcg.io/sm8/203.png","imageLarge":"https://images.pokemontcg.io/sm8/203_hires.png"},{"id":"sm8-223","name":"Tyranitar-GX","set":"Lost Thunder","setId":"sm8","number":"223","rarity":"Rare Rainbow","types":["Darkness"],"hp":"250","artist":"5ban Graphics","imageSmall":"https://images.pokemontcg.io/sm8/223.png","imageLarge":"https://images.pokemontcg.io/sm8/223_hires.png"},{"id":"sm6-69","name":"Tyrantrum","set":"Forbidden Light","setId":"sm6","number":"69","rarity":"Rare Holo","types":["Fighting"],"hp":"160","artist":"hatachu","imageSmall":"https://images.pokemontcg.io/sm6/69.png","imageLarge":"https://images.pokemontcg.io/sm6/69_hires.png"},{"id":"xy3-62","name":"Tyrantrum","set":"Furious Fists","setId":"xy3","number":"62","rarity":"Rare","types":["Fighting"],"hp":"150","artist":"5ban Graphics","imageSmall":"https://images.pokemontcg.io/xy3/62.png","imageLarge":"https://images.pokemontcg.io/xy3/62_hires.png"},{"id":"xyp-XY70","name":"Tyrantrum-EX","set":"XY Black Star Promos","setId":"xyp","number":"XY70","rarity":"Promo","types":["Dragon"],"hp":"180","artist":"Eske Yoshinob","imageSmall":"https://images.pokemontcg.io/xyp/XY70.png","imageLarge":"https://images.pokemontcg.io/xyp/XY70_hires.png"},{"id":"col1-36","name":"Tyrogue","set":"Call of Legends","setId":"col1","number":"36","rarity":"Rare","types":["Fighting"],"hp":"30","artist":"Shigenori Negishi","imageSmall":"https://images.pokemontcg.io/col1/36.png","imageLarge":"https://images.pokemontcg.io/col1/36_hires.png"},{"id":"dp6-126","name":"Tyrogue","set":"Legends Awakened","setId":"dp6","number":"126","rarity":"Common","types":["Fighting"],"hp":"60","artist":"Kagemaru Himeno","imageSmall":"https://images.pokemontcg.io/dp6/126.png","imageLarge":"https://images.pokemontcg.io/dp6/126_hires.png"},{"id":"ecard2-63","name":"Tyrogue","set":"Aquapolis","setId":"ecard2","number":"63","rarity":"Uncommon","types":["Fighting"],"hp":"30","artist":"Tomokazu Komiya","imageSmall":"https://images.pokemontcg.io/ecard2/63.png","imageLarge":"https://images.pokemontcg.io/ecard2/63_hires.png"},{"id":"ex10-33","name":"Tyrogue","set":"Unseen Forces","setId":"ex10","number":"33","rarity":"Rare","types":["Fighting"],"hp":"40","artist":"Yuka Morii","imageSmall":"https://images.pokemontcg.io/ex10/33.png","imageLarge":"https://images.pokemontcg.io/ex10/33_hires.png"},{"id":"hgss1-33","name":"Tyrogue","set":"HeartGold & SoulSilver","setId":"hgss1","number":"33","rarity":"Rare","types":["Fighting"],"hp":"30","artist":"Ken Sugimori","imageSmall":"https://images.pokemontcg.io/hgss1/33.png","imageLarge":"https://images.pokemontcg.io/hgss1/33_hires.png"},{"id":"me1-71","name":"Tyrogue","set":"Mega Evolution","setId":"me1","number":"71","rarity":"Common","types":["Fighting"],"hp":"30","artist":null,"imageSmall":"https://images.pokemontcg.io/me1/71.png","imageLarge":"https://images.pokemontcg.io/me1/71_hires.png"},{"id":"neo2-66","name":"Tyrogue","set":"Neo Discovery","setId":"neo2","number":"66","rarity":"Common","types":["Fighting"],"hp":"30","artist":"Miki Tanaka","imageSmall":"https://images.pokemontcg.io/neo2/66.png","imageLarge":"https://images.pokemontcg.io/neo2/66_hires.png"},{"id":"sm10-100","name":"Tyrogue","set":"Unbroken Bonds","setId":"sm10","number":"100","rarity":"Uncommon","types":["Fighting"],"hp":"60","artist":"Mina Nakai","imageSmall":"https://images.pokemontcg.io/sm10/100.png","imageLarge":"https://images.pokemontcg.io/sm10/100_hires.png"},{"id":"sm6-68","name":"Tyrunt","set":"Forbidden Light","setId":"sm6","number":"68","rarity":"Uncommon","types":["Fighting"],"hp":"90","artist":"SATOSHI NAKAI","imageSmall":"https://images.pokemontcg.io/sm6/68.png","imageLarge":"https://images.pokemontcg.io/sm6/68_hires.png"},{"id":"xy3-61","name":"Tyrunt","set":"Furious Fists","setId":"xy3","number":"61","rarity":"Uncommon","types":["Fighting"],"hp":"90","artist":"5ban Graphics","imageSmall":"https://images.pokemontcg.io/xy3/61.png","imageLarge":"https://images.pokemontcg.io/xy3/61_hires.png"}]