{"id":"sv6pt5","name":"Shrouded Fable","series":"Scarlet & Violet","printedTotal":64,"total":99,"cardCount":99,"releaseDate":"2024/08/02","updatedAt":"2024/08/02 15:00:00","symbolImage":"https://images.pokemontcg.io/sv6pt5/symbol.png","logoImage":"https://images.pokemontcg.io/sv6pt5/logo.png","cards":[{"id":"sv6pt5-1","name":"Joltik","set":"Shrouded Fable","setId":"sv6pt5","number":"1","rarity":"Common","types":["Grass"],"hp":"40","artist":"Naoyo Kimura","imageSmall":"https://images.pokemontcg.io/sv6pt5/1.png","imageLarge":"https://images.pokemontcg.io/sv6pt5/1_hires.png"},{"id":"sv6pt5-2","name":"Galvantula","set":"Shrouded Fable","setId":"sv6pt5","number":"2","rarity":"Uncommon","types":["Grass"],"hp":"100","artist":"mashu","imageSmall":"https://images.pokemontcg.io/sv6pt5/2.png","imageLarge":"https://images.pokemontcg.io/sv6pt5/2_hires.png"},{"id":"sv6pt5-3","name":"Rowlet","set":"Shrouded Fable","setId":"sv6pt5","number":"3","rarity":"Common","types":["Grass"],"hp":"70","artist":"Yoshimi Miyoshi","imageSmall":"https://images.pokemontcg.io/sv6pt5/3.png","imageLarge":"https://images.pokemontcg.io/sv6pt5/3_hires.png"},{"id":"sv6pt5-4","name":"Dartrix","set":"Shrouded Fable","setId":"sv6pt5","number":"4","rarity":"Common","types":["Grass"],"hp":"90","artist":"Tetsu Kayama","imageSmall":"https://images.pokemontcg.io/sv6pt5/4.png","imageLarge":"https://images.pokemontcg.io/sv6pt5/4_hires.png"},{"id":"sv6pt5-5","name":"Decidueye","set":"Shrouded Fable","setId":"sv6pt5","number":"5","rarity":"Uncommon","types":["Grass"],"hp":"150","artist":"DOM","imageSmall":"https://images.pokemontcg.io/sv6pt5/5.png","imageLarge":"https://images.pokemontcg.io/sv6pt5/5_hires.png"},{"id":"sv6pt5-6","name":"Tapu Bulu","set":"Shrouded Fable","setId":"sv6pt5","number":"6","rarity":"Rare","types":["Grass"],"hp":"140","artist":"GOSSAN","imageSmall":"https://images.pokemontcg.io/sv6pt5/6.png","imageLarge":"https://images.pokemontcg.io/sv6pt5/6_hires.png"},{"id":"sv6pt5-7","name":"Houndour","set":"Shrouded Fable","setId":"sv6pt5","number":"7","rarity":"Common","types":["Fire"],"hp":"70","artist":"REND","imageSmall":"https://images.pokemontcg.io/sv6pt5/7.png","imageLarge":"https://images.pokemontcg.io/sv6pt5/7_hires.png"},{"id":"sv6pt5-8","name":"Houndoom","set":"Shrouded Fable","setId":"sv6pt5","number":"8","rarity":"Common","types":["Fire"],"hp":"120","artist":"burari","imageSmall":"https://images.pokemontcg.io/sv6pt5/8.png","imageLarge":"https://images.pokemontcg.io/sv6pt5/8_hires.png"},{"id":"sv6pt5-9","name":"Iron Moth","set":"Shrouded Fable","setId":"sv6pt5","number":"9","rarity":"Uncommon","types":["Fire"],"hp":"120","artist":"Shinji Kanda","imageSmall":"https://images.pokemontcg.io/sv6pt5/9.png","imageLarge":"https://images.pokemontcg.io/sv6pt5/9_hires.png"},{"id":"sv6pt5-10","name":"Horsea","set":"Shrouded Fable","setId":"sv6pt5","number":"10","rarity":"Common","types":["Water"],"hp":"60","artist":"Shimaris Yukichi","imageSmall":"https://images.pokemontcg.io/sv6pt5/10.png","imageLarge":"https://images.pokemontcg.io/sv6pt5/10_hires.png"},{"id":"sv6pt5-11","name":"Seadra","set":"Shrouded Fable","setId":"sv6pt5","number":"11","rarity":"Common","types":["Water"],"hp":"90","artist":"Yuya Oka","imageSmall":"https://images.pokemontcg.io/sv6pt5/11.png","imageLarge":"https://images.pokemontcg.io/sv6pt5/11_hires.png"},{"id":"sv6pt5-12","name":"Kingdra ex","set":"Shrouded Fable","setId":"sv6pt5","number":"12","rarity":"Double Rare","types":["Water"],"hp":"310","artist":"toriyufu","imageSmall":"https://images.pokemontcg.io/sv6pt5/12.png","imageLarge":"https://images.pokemontcg.io/sv6pt5/12_hires.png"},{"id":"sv6pt5-13","name":"Sneasel","set":"Shrouded Fable","setId":"sv6pt5","number":"13","rarity":"Common","types":["Water"],"hp":"70","artist":"Krgc","imageSmall":"https://images.pokemontcg.io/sv6pt5/13.png","imageLarge":"https://images.pokemontcg.io/sv6pt5/13_hires.png"},{"id":"sv6pt5-14","name":"Weavile","set":"Shrouded Fable","setId":"sv6pt5","number":"14","rarity":"Uncommon","types":["Water"],"hp":"100","artist":"aspara","imageSmall":"https://images.pokemontcg.io/sv6pt5/14.png","imageLarge":"https://images.pokemontcg.io/sv6pt5/14_hires.png"},{"id":"sv6pt5-15","name":"Revavroom ex","set":"Shrouded Fable","setId":"sv6pt5","number":"15","rarity":"Double Rare","types":["Lightning"],"hp":"280","artist":"PLANETA Mochizuki","imageSmall":"https://images.pokemontcg.io/sv6pt5/15.png","imageLarge":"https://images.pokemontcg.io/sv6pt5/15_hires.png"},{"id":"sv6pt5-16","name":"Drowzee","set":"Shrouded Fable","setId":"sv6pt5","number":"16","rarity":"Common","types":["Psychic"],"hp":"70","artist":"OKUBO","imageSmall":"https://images.pokemontcg.io/sv6pt5/16.png","imageLarge":"https://images.pokemontcg.io/sv6pt5/16_hires.png"},{"id":"sv6pt5-17","name":"Hypno","set":"Shrouded Fable","setId":"sv6pt5","number":"17","rarity":"Uncommon","types":["Psychic"],"hp":"110","artist":"Masako Tomii","imageSmall":"https://images.pokemontcg.io/sv6pt5/17.png","imageLarge":"https://images.pokemontcg.io/sv6pt5/17_hires.png"},{"id":"sv6pt5-18","name":"Duskull","set":"Shrouded Fable","setId":"sv6pt5","number":"18","rarity":"Common","types":["Psychic"],"hp":"60","artist":"IKEDA Saki","imageSmall":"https://images.pokemontcg.io/sv6pt5/18.png","imageLarge":"https://images.pokemontcg.io/sv6pt5/18_hires.png"},{"id":"sv6pt5-19","name":"Dusclops","set":"Shrouded Fable","setId":"sv6pt5","number":"19","rarity":"Common","types":["Psychic"],"hp":"90","artist":"Aya Kusube","imageSmall":"https://images.pokemontcg.io/sv6pt5/19.png","imageLarge":"https://images.pokemontcg.io/sv6pt5/19_hires.png"},{"id":"sv6pt5-20","name":"Dusknoir","set":"Shrouded Fable","setId":"sv6pt5","number":"20","rarity":"Rare","types":["Psychic"],"hp":"160","artist":"danciao","imageSmall":"https://images.pokemontcg.io/sv6pt5/20.png","imageLarge":"https://images.pokemontcg.io/sv6pt5/20_hires.png"},{"id":"sv6pt5-21","name":"Cresselia","set":"Shrouded Fable","setId":"sv6pt5","number":"21","rarity":"Rare","types":["Psychic"],"hp":"120","artist":"matazo","imageSmall":"https://images.pokemontcg.io/sv6pt5/21.png","imageLarge":"https://images.pokemontcg.io/sv6pt5/21_hires.png"},{"id":"sv6pt5-22","name":"Sylveon","set":"Shrouded Fable","setId":"sv6pt5","number":"22","rarity":"Uncommon","types":["Psychic"],"hp":"120","artist":"Kuroimori","imageSmall":"https://images.pokemontcg.io/sv6pt5/22.png","imageLarge":"https://images.pokemontcg.io/sv6pt5/22_hires.png"},{"id":"sv6pt5-23","name":"Croagunk","set":"Shrouded Fable","setId":"sv6pt5","number":"23","rarity":"Common","types":["Fighting"],"hp":"70","artist":"Aliya Chen","imageSmall":"https://images.pokemontcg.io/sv6pt5/23.png","imageLarge":"https://images.pokemontcg.io/sv6pt5/23_hires.png"},{"id":"sv6pt5-24","name":"Toxicroak","set":"Shrouded Fable","setId":"sv6pt5","number":"24","rarity":"Common","types":["Fighting"],"hp":"130","artist":"Anesaki Dynamic","imageSmall":"https://images.pokemontcg.io/sv6pt5/24.png","imageLarge":"https://images.pokemontcg.io/sv6pt5/24_hires.png"},{"id":"sv6pt5-25","name":"Bloodmoon Ursaluna","set":"Shrouded Fable","setId":"sv6pt5","number":"25","rarity":"Rare","types":["Fighting"],"hp":"150","artist":"Souichirou Gunjima","imageSmall":"https://images.pokemontcg.io/sv6pt5/25.png","imageLarge":"https://images.pokemontcg.io/sv6pt5/25_hires.png"},{"id":"sv6pt5-26","name":"Slither Wing","set":"Shrouded Fable","setId":"sv6pt5","number":"26","rarity":"Uncommon","types":["Fighting"],"hp":"140","artist":"Shinji Kanda","imageSmall":"https://images.pokemontcg.io/sv6pt5/26.png","imageLarge":"https://images.pokemontcg.io/sv6pt5/26_hires.png"},{"id":"sv6pt5-27","name":"Zubat","set":"Shrouded Fable","setId":"sv6pt5","number":"27","rarity":"Common","types":["Darkness"],"hp":"50","artist":"osare","imageSmall":"https://images.pokemontcg.io/sv6pt5/27.png","imageLarge":"https://images.pokemontcg.io/sv6pt5/27_hires.png"},{"id":"sv6pt5-28","name":"Golbat","set":"Shrouded Fable","setId":"sv6pt5","number":"28","rarity":"Common","types":["Darkness"],"hp":"80","artist":"Teeziro","imageSmall":"https://images.pokemontcg.io/sv6pt5/28.png","imageLarge":"https://images.pokemontcg.io/sv6pt5/28_hires.png"},{"id":"sv6pt5-29","name":"Crobat","set":"Shrouded Fable","setId":"sv6pt5","number":"29","rarity":"Uncommon","types":["Darkness"],"hp":"130","artist":"Nisota Niso","imageSmall":"https://images.pokemontcg.io/sv6pt5/29.png","imageLarge":"https://images.pokemontcg.io/sv6pt5/29_hires.png"},{"id":"sv6pt5-30","name":"Absol","set":"Shrouded Fable","setId":"sv6pt5","number":"30","rarity":"Common","types":["Darkness"],"hp":"110","artist":"rika","imageSmall":"https://images.pokemontcg.io/sv6pt5/30.png","imageLarge":"https://images.pokemontcg.io/sv6pt5/30_hires.png"},{"id":"sv6pt5-31","name":"Zorua","set":"Shrouded Fable","setId":"sv6pt5","number":"31","rarity":"Common","types":["Darkness"],"hp":"70","artist":"Yuu Nishida","imageSmall":"https://images.pokemontcg.io/sv6pt5/31.png","imageLarge":"https://images.pokemontcg.io/sv6pt5/31_hires.png"},{"id":"sv6pt5-32","name":"Zoroark","set":"Shrouded Fable","setId":"sv6pt5","number":"32","rarity":"Rare","types":["Darkness"],"hp":"120","artist":"nagimiso","imageSmall":"https://images.pokemontcg.io/sv6pt5/32.png","imageLarge":"https://images.pokemontcg.io/sv6pt5/32_hires.png"},{"id":"sv6pt5-33","name":"Inkay","set":"Shrouded Fable","setId":"sv6pt5","number":"33","rarity":"Common","types":["Darkness"],"hp":"60","artist":"Mori Yuu","imageSmall":"https://images.pokemontcg.io/sv6pt5/33.png","imageLarge":"https://images.pokemontcg.io/sv6pt5/33_hires.png"},{"id":"sv6pt5-34","name":"Malamar","set":"Shrouded Fable","setId":"sv6pt5","number":"34","rarity":"Uncommon","types":["Darkness"],"hp":"120","artist":"akagi","imageSmall":"https://images.pokemontcg.io/sv6pt5/34.png","imageLarge":"https://images.pokemontcg.io/sv6pt5/34_hires.png"},{"id":"sv6pt5-35","name":"Yveltal","set":"Shrouded Fable","setId":"sv6pt5","number":"35","rarity":"Uncommon","types":["Darkness"],"hp":"120","artist":"SIE NANAHARA","imageSmall":"https://images.pokemontcg.io/sv6pt5/35.png","imageLarge":"https://images.pokemontcg.io/sv6pt5/35_hires.png"},{"id":"sv6pt5-36","name":"Okidogi ex","set":"Shrouded Fable","setId":"sv6pt5","number":"36","rarity":"Double Rare","types":["Darkness"],"hp":"250","artist":"takuyoa","imageSmall":"https://images.pokemontcg.io/sv6pt5/36.png","imageLarge":"https://images.pokemontcg.io/sv6pt5/36_hires.png"},{"id":"sv6pt5-37","name":"Munkidori ex","set":"Shrouded Fable","setId":"sv6pt5","number":"37","rarity":"Double Rare","types":["Darkness"],"hp":"210","artist":"takuyoa","imageSmall":"https://images.pokemontcg.io/sv6pt5/37.png","imageLarge":"https://images.pokemontcg.io/sv6pt5/37_hires.png"},{"id":"sv6pt5-38","name":"Fezandipiti ex","set":"Shrouded Fable","setId":"sv6pt5","number":"38","rarity":"Double Rare","types":["Darkness"],"hp":"210","artist":"takuyoa","imageSmall":"https://images.pokemontcg.io/sv6pt5/38.png","imageLarge":"https://images.pokemontcg.io/sv6pt5/38_hires.png"},{"id":"sv6pt5-39","name":"Pecharunt ex","set":"Shrouded Fable","setId":"sv6pt5","number":"39","rarity":"Double Rare","types":["Darkness"],"hp":"190","artist":"aky CG Works","imageSmall":"https://images.pokemontcg.io/sv6pt5/39.png","imageLarge":"https://images.pokemontcg.io/sv6pt5/39_hires.png"},{"id":"sv6pt5-40","name":"Genesect","set":"Shrouded Fable","setId":"sv6pt5","number":"40","rarity":"Uncommon","types":["Metal"],"hp":"110","artist":"Kazumasa Yasukuni","imageSmall":"https://images.pokemontcg.io/sv6pt5/40.png","imageLarge":"https://images.pokemontcg.io/sv6pt5/40_hires.png"},{"id":"sv6pt5-41","name":"Cufant","set":"Shrouded Fable","setId":"sv6pt5","number":"41","rarity":"Common","types":["Metal"],"hp":"100","artist":"Shinya Mizuno","imageSmall":"https://images.pokemontcg.io/sv6pt5/41.png","imageLarge":"https://images.pokemontcg.io/sv6pt5/41_hires.png"},{"id":"sv6pt5-42","name":"Copperajah","set":"Shrouded Fable","setId":"sv6pt5","number":"42","rarity":"Rare","types":["Metal"],"hp":"200","artist":"kawayoo","imageSmall":"https://images.pokemontcg.io/sv6pt5/42.png","imageLarge":"https://images.pokemontcg.io/sv6pt5/42_hires.png"},{"id":"sv6pt5-43","name":"Varoom","set":"Shrouded Fable","setId":"sv6pt5","number":"43","rarity":"Common","types":["Metal"],"hp":"70","artist":"HAGIYA Kaoru","imageSmall":"https://images.pokemontcg.io/sv6pt5/43.png","imageLarge":"https://images.pokemontcg.io/sv6pt5/43_hires.png"},{"id":"sv6pt5-44","name":"Axew","set":"Shrouded Fable","setId":"sv6pt5","number":"44","rarity":"Common","types":["Dragon"],"hp":"70","artist":"Orca","imageSmall":"https://images.pokemontcg.io/sv6pt5/44.png","imageLarge":"https://images.pokemontcg.io/sv6pt5/44_hires.png"},{"id":"sv6pt5-45","name":"Fraxure","set":"Shrouded Fable","setId":"sv6pt5","number":"45","rarity":"Common","types":["Dragon"],"hp":"100","artist":"Uninori","imageSmall":"https://images.pokemontcg.io/sv6pt5/45.png","imageLarge":"https://images.pokemontcg.io/sv6pt5/45_hires.png"},{"id":"sv6pt5-46","name":"Haxorus","set":"Shrouded Fable","setId":"sv6pt5","number":"46","rarity":"Rare","types":["Dragon"],"hp":"170","artist":"Tsuyoshi Nagano","imageSmall":"https://images.pokemontcg.io/sv6pt5/46.png","imageLarge":"https://images.pokemontcg.io/sv6pt5/46_hires.png"},{"id":"sv6pt5-47","name":"Kyurem","set":"Shrouded Fable","setId":"sv6pt5","number":"47","rarity":"Uncommon","types":["Dragon"],"hp":"130","artist":"Shiburingaru","imageSmall":"https://images.pokemontcg.io/sv6pt5/47.png","imageLarge":"https://images.pokemontcg.io/sv6pt5/47_hires.png"},{"id":"sv6pt5-48","name":"Meowth","set":"Shrouded Fable","setId":"sv6pt5","number":"48","rarity":"Common","types":["Colorless"],"hp":"70","artist":"sui","imageSmall":"https://images.pokemontcg.io/sv6pt5/48.png","imageLarge":"https://images.pokemontcg.io/sv6pt5/48_hires.png"},{"id":"sv6pt5-49","name":"Persian","set":"Shrouded Fable","setId":"sv6pt5","number":"49","rarity":"Common","types":["Colorless"],"hp":"110","artist":"NC Empire","imageSmall":"https://images.pokemontcg.io/sv6pt5/49.png","imageLarge":"https://images.pokemontcg.io/sv6pt5/49_hires.png"},{"id":"sv6pt5-50","name":"Eevee","set":"Shrouded Fable","setId":"sv6pt5","number":"50","rarity":"Common","types":["Colorless"],"hp":"70","artist":"Susumu Maeya","imageSmall":"https://images.pokemontcg.io/sv6pt5/50.png","imageLarge":"https://images.pokemontcg.io/sv6pt5/50_hires.png"},{"id":"sv6pt5-51","name":"Furfrou","set":"Shrouded Fable","setId":"sv6pt5","number":"51","rarity":"Common","types":["Colorless"],"hp":"100","artist":"Shinya Komatsu","imageSmall":"https://images.pokemontcg.io/sv6pt5/51.png","imageLarge":"https://images.pokemontcg.io/sv6pt5/51_hires.png"},{"id":"sv6pt5-52","name":"Stufful","set":"Shrouded Fable","setId":"sv6pt5","number":"52","rarity":"Common","types":["Colorless"],"hp":"80","artist":"ryoma uratsuka","imageSmall":"https://images.pokemontcg.io/sv6pt5/52.png","imageLarge":"https://images.pokemontcg.io/sv6pt5/52_hires.png"},{"id":"sv6pt5-53","name":"Bewear","set":"Shrouded Fable","setId":"sv6pt5","number":"53","rarity":"Common","types":["Colorless"],"hp":"130","artist":"Takeshi Nakamura","imageSmall":"https://images.pokemontcg.io/sv6pt5/53.png","imageLarge":"https://images.pokemontcg.io/sv6pt5/53_hires.png"},{"id":"sv6pt5-54","name":"Academy at Night","set":"Shrouded Fable","setId":"sv6pt5","number":"54","rarity":"Uncommon","types":[],"hp":null,"artist":"AYUMI ODASHIMA","imageSmall":"https://images.pokemontcg.io/sv6pt5/54.png","imageLarge":"https://images.pokemontcg.io/sv6pt5/54_hires.png"},{"id":"sv6pt5-55","name":"Binding Mochi","set":"Shrouded Fable","setId":"sv6pt5","number":"55","rarity":"Uncommon","types":[],"hp":null,"artist":"5ban Graphics","imageSmall":"https://images.pokemontcg.io/sv6pt5/55.png","imageLarge":"https://images.pokemontcg.io/sv6pt5/55_hires.png"},{"id":"sv6pt5-56","name":"Cassiopeia","set":"Shrouded Fable","setId":"sv6pt5","number":"56","rarity":"Uncommon","types":[],"hp":null,"artist":"Atsushi Furusawa","imageSmall":"https://images.pokemontcg.io/sv6pt5/56.png","imageLarge":"https://images.pokemontcg.io/sv6pt5/56_hires.png"},{"id":"sv6pt5-57","name":"Colress's Tenacity","set":"Shrouded Fable","setId":"sv6pt5","number":"57","rarity":"Uncommon","types":[],"hp":null,"artist":"hncl","imageSmall":"https://images.pokemontcg.io/sv6pt5/57.png","imageLarge":"https://images.pokemontcg.io/sv6pt5/57_hires.png"},{"id":"sv6pt5-58","name":"Dangerous Laser","set":"Shrouded Fable","setId":"sv6pt5","number":"58","rarity":"ACE SPEC Rare","types":[],"hp":null,"artist":"inose yukie","imageSmall":"https://images.pokemontcg.io/sv6pt5/58.png","imageLarge":"https://images.pokemontcg.io/sv6pt5/58_hires.png"},{"id":"sv6pt5-59","name":"Janine's Secret Art","set":"Shrouded Fable","setId":"sv6pt5","number":"59","rarity":"Uncommon","types":[],"hp":null,"artist":"Taira Akitsu","imageSmall":"https://images.pokemontcg.io/sv6pt5/59.png","imageLarge":"https://images.pokemontcg.io/sv6pt5/59_hires.png"},{"id":"sv6pt5-60","name":"Neutralization Zone","set":"Shrouded Fable","setId":"sv6pt5","number":"60","rarity":"ACE SPEC Rare","types":[],"hp":null,"artist":"imoniii","imageSmall":"https://images.pokemontcg.io/sv6pt5/60.png","imageLarge":"https://images.pokemontcg.io/sv6pt5/60_hires.png"},{"id":"sv6pt5-61","name":"Night Stretcher","set":"Shrouded Fable","setId":"sv6pt5","number":"61","rarity":"Uncommon","types":[],"hp":null,"artist":"Toyste Beach","imageSmall":"https://images.pokemontcg.io/sv6pt5/61.png","imageLarge":"https://images.pokemontcg.io/sv6pt5/61_hires.png"},{"id":"sv6pt5-62","name":"Poké Vital A","set":"Shrouded Fable","setId":"sv6pt5","number":"62","rarity":"ACE SPEC Rare","types":[],"hp":null,"artist":"Toyste Beach","imageSmall":"https://images.pokemontcg.io/sv6pt5/62.png","imageLarge":"https://images.pokemontcg.io/sv6pt5/62_hires.png"},{"id":"sv6pt5-63","name":"Powerglass","set":"Shrouded Fable","setId":"sv6pt5","number":"63","rarity":"Uncommon","types":[],"hp":null,"artist":"Studio Bora Inc.","imageSmall":"https://images.pokemontcg.io/sv6pt5/63.png","imageLarge":"https://images.pokemontcg.io/sv6pt5/63_hires.png"},{"id":"sv6pt5-64","name":"Xerosic's Machinations","set":"Shrouded Fable","setId":"sv6pt5","number":"64","rarity":"Uncommon","types":[],"hp":null,"artist":"GOSSAN","imageSmall":"https://images.pokemontcg.io/sv6pt5/64.png","imageLarge":"https://images.pokemontcg.io/sv6pt5/64_hires.png"},{"id":"sv6pt5-65","name":"Tapu Bulu","set":"Shrouded Fable","setId":"sv6pt5","number":"65","rarity":"Illustration Rare","types":["Grass"],"hp":"140","artist":"IKEDA Saki","imageSmall":"https://images.pokemontcg.io/sv6pt5/65.png","imageLarge":"https://images.pokemontcg.io/sv6pt5/65_hires.png"},{"id":"sv6pt5-66","name":"Houndoom","set":"Shrouded Fable","setId":"sv6pt5","number":"66","rarity":"Illustration Rare","types":["Fire"],"hp":"120","artist":"Taiga Kasai","imageSmall":"https://images.pokemontcg.io/sv6pt5/66.png","imageLarge":"https://images.pokemontcg.io/sv6pt5/66_hires.png"},{"id":"sv6pt5-67","name":"Horsea","set":"Shrouded Fable","setId":"sv6pt5","number":"67","rarity":"Illustration Rare","types":["Water"],"hp":"60","artist":"Shinya Komatsu","imageSmall":"https://images.pokemontcg.io/sv6pt5/67.png","imageLarge":"https://images.pokemontcg.io/sv6pt5/67_hires.png"},{"id":"sv6pt5-68","name":"Duskull","set":"Shrouded Fable","setId":"sv6pt5","number":"68","rarity":"Illustration Rare","types":["Psychic"],"hp":"60","artist":"James Turner","imageSmall":"https://images.pokemontcg.io/sv6pt5/68.png","imageLarge":"https://images.pokemontcg.io/sv6pt5/68_hires.png"},{"id":"sv6pt5-69","name":"Dusclops","set":"Shrouded Fable","setId":"sv6pt5","number":"69","rarity":"Illustration Rare","types":["Psychic"],"hp":"90","artist":"James Turner","imageSmall":"https://images.pokemontcg.io/sv6pt5/69.png","imageLarge":"https://images.pokemontcg.io/sv6pt5/69_hires.png"},{"id":"sv6pt5-70","name":"Dusknoir","set":"Shrouded Fable","setId":"sv6pt5","number":"70","rarity":"Illustration Rare","types":["Psychic"],"hp":"160","artist":"James Turner","imageSmall":"https://images.pokemontcg.io/sv6pt5/70.png","imageLarge":"https://images.pokemontcg.io/sv6pt5/70_hires.png"},{"id":"sv6pt5-71","name":"Cresselia","set":"Shrouded Fable","setId":"sv6pt5","number":"71","rarity":"Illustration Rare","types":["Psychic"],"hp":"120","artist":"satoma","imageSmall":"https://images.pokemontcg.io/sv6pt5/71.png","imageLarge":"https://images.pokemontcg.io/sv6pt5/71_hires.png"},{"id":"sv6pt5-72","name":"Munkidori","set":"Shrouded Fable","setId":"sv6pt5","number":"72","rarity":"Illustration Rare","types":["Psychic"],"hp":"110","artist":"Teeziro","imageSmall":"https://images.pokemontcg.io/sv6pt5/72.png","imageLarge":"https://images.pokemontcg.io/sv6pt5/72_hires.png"},{"id":"sv6pt5-73","name":"Fezandipiti","set":"Shrouded Fable","setId":"sv6pt5","number":"73","rarity":"Illustration Rare","types":["Psychic"],"hp":"120","artist":"KEIICHIRO ITO","imageSmall":"https://images.pokemontcg.io/sv6pt5/73.png","imageLarge":"https://images.pokemontcg.io/sv6pt5/73_hires.png"},{"id":"sv6pt5-74","name":"Okidogi","set":"Shrouded Fable","setId":"sv6pt5","number":"74","rarity":"Illustration Rare","types":["Fighting"],"hp":"130","artist":"AKIRA EGAWA","imageSmall":"https://images.pokemontcg.io/sv6pt5/74.png","imageLarge":"https://images.pokemontcg.io/sv6pt5/74_hires.png"},{"id":"sv6pt5-75","name":"Zorua","set":"Shrouded Fable","setId":"sv6pt5","number":"75","rarity":"Illustration Rare","types":["Darkness"],"hp":"70","artist":"REND","imageSmall":"https://images.pokemontcg.io/sv6pt5/75.png","imageLarge":"https://images.pokemontcg.io/sv6pt5/75_hires.png"},{"id":"sv6pt5-76","name":"Cufant","set":"Shrouded Fable","setId":"sv6pt5","number":"76","rarity":"Illustration Rare","types":["Metal"],"hp":"100","artist":"Mina Nakai","imageSmall":"https://images.pokemontcg.io/sv6pt5/76.png","imageLarge":"https://images.pokemontcg.io/sv6pt5/76_hires.png"},{"id":"sv6pt5-77","name":"Fraxure","set":"Shrouded Fable","setId":"sv6pt5","number":"77","rarity":"Illustration Rare","types":["Dragon"],"hp":"100","artist":"MINAMINAMI Take","imageSmall":"https://images.pokemontcg.io/sv6pt5/77.png","imageLarge":"https://images.pokemontcg.io/sv6pt5/77_hires.png"},{"id":"sv6pt5-78","name":"Persian","set":"Shrouded Fable","setId":"sv6pt5","number":"78","rarity":"Illustration Rare","types":["Colorless"],"hp":"110","artist":"Whisker","imageSmall":"https://images.pokemontcg.io/sv6pt5/78.png","imageLarge":"https://images.pokemontcg.io/sv6pt5/78_hires.png"},{"id":"sv6pt5-79","name":"Bewear","set":"Shrouded Fable","setId":"sv6pt5","number":"79","rarity":"Illustration Rare","types":["Colorless"],"hp":"130","artist":"Takeshi Nakamura","imageSmall":"https://images.pokemontcg.io/sv6pt5/79.png","imageLarge":"https://images.pokemontcg.io/sv6pt5/79_hires.png"},{"id":"sv6pt5-80","name":"Kingdra ex","set":"Shrouded Fable","setId":"sv6pt5","number":"80","rarity":"Ultra Rare","types":["Water"],"hp":"310","artist":"PLANETA Igarashi","imageSmall":"https://images.pokemontcg.io/sv6pt5/80.png","imageLarge":"https://images.pokemontcg.io/sv6pt5/80_hires.png"},{"id":"sv6pt5-81","name":"Revavroom ex","set":"Shrouded Fable","setId":"sv6pt5","number":"81","rarity":"Ultra Rare","types":["Lightning"],"hp":"280","artist":"PLANETA Mochizuki","imageSmall":"https://images.pokemontcg.io/sv6pt5/81.png","imageLarge":"https://images.pokemontcg.io/sv6pt5/81_hires.png"},{"id":"sv6pt5-82","name":"Okidogi ex","set":"Shrouded Fable","setId":"sv6pt5","number":"82","rarity":"Ultra Rare","types":["Darkness"],"hp":"250","artist":"5ban Graphics","imageSmall":"https://images.pokemontcg.io/sv6pt5/82.png","imageLarge":"https://images.pokemontcg.io/sv6pt5/82_hires.png"},{"id":"sv6pt5-83","name":"Munkidori ex","set":"Shrouded Fable","setId":"sv6pt5","number":"83","rarity":"Ultra Rare","types":["Darkness"],"hp":"210","artist":"5ban Graphics","imageSmall":"https://images.pokemontcg.io/sv6pt5/83.png","imageLarge":"https://images.pokemontcg.io/sv6pt5/83_hires.png"},{"id":"sv6pt5-84","name":"Fezandipiti ex","set":"Shrouded Fable","setId":"sv6pt5","number":"84","rarity":"Ultra Rare","types":["Darkness"],"hp":"210","artist":"5ban Graphics","imageSmall":"https://images.pokemontcg.io/sv6pt5/84.png","imageLarge":"https://images.pokemontcg.io/sv6pt5/84_hires.png"},{"id":"sv6pt5-85","name":"Pecharunt ex","set":"Shrouded Fable","setId":"sv6pt5","number":"85","rarity":"Ultra Rare","types":["Darkness"],"hp":"190","artist":"aky CG Works","imageSmall":"https://images.pokemontcg.io/sv6pt5/85.png","imageLarge":"https://images.pokemontcg.io/sv6pt5/85_hires.png"},{"id":"sv6pt5-86","name":"Cassiopeia","set":"Shrouded Fable","setId":"sv6pt5","number":"86","rarity":"Ultra Rare","types":[],"hp":null,"artist":"Atsushi Furusawa","imageSmall":"https://images.pokemontcg.io/sv6pt5/86.png","imageLarge":"https://images.pokemontcg.io/sv6pt5/86_hires.png"},{"id":"sv6pt5-87","name":"Colress's Tenacity","set":"Shrouded Fable","setId":"sv6pt5","number":"87","rarity":"Ultra Rare","types":[],"hp":null,"artist":"hncl","imageSmall":"https://images.pokemontcg.io/sv6pt5/87.png","imageLarge":"https://images.pokemontcg.io/sv6pt5/87_hires.png"},{"id":"sv6pt5-88","name":"Janine's Secret Art","set":"Shrouded Fable","setId":"sv6pt5","number":"88","rarity":"Ultra Rare","types":[],"hp":null,"artist":"Taira Akitsu","imageSmall":"https://images.pokemontcg.io/sv6pt5/88.png","imageLarge":"https://images.pokemontcg.io/sv6pt5/88_hires.png"},{"id":"sv6pt5-89","name":"Xerosic's Machinations","set":"Shrouded Fable","setId":"sv6pt5","number":"89","rarity":"Ultra Rare","types":[],"hp":null,"artist":"GOSSAN","imageSmall":"https://images.pokemontcg.io/sv6pt5/89.png","imageLarge":"https://images.pokemontcg.io/sv6pt5/89_hires.png"},{"id":"sv6pt5-90","name":"Okidogi ex","set":"Shrouded Fable","setId":"sv6pt5","number":"90","rarity":"Special Illustration Rare","types":["Darkness"],"hp":"250","artist":"kantaro","imageSmall":"https://images.pokemontcg.io/sv6pt5/90.png","imageLarge":"https://images.pokemontcg.io/sv6pt5/90_hires.png"},{"id":"sv6pt5-91","name":"Munkidori ex","set":"Shrouded Fable","setId":"sv6pt5","number":"91","rarity":"Special Illustration Rare","types":["Darkness"],"hp":"210","artist":"kantaro","imageSmall":"https://images.pokemontcg.io/sv6pt5/91.png","imageLarge":"https://images.pokemontcg.io/sv6pt5/91_hires.png"},{"id":"sv6pt5-92","name":"Fezandipiti ex","set":"Shrouded Fable","setId":"sv6pt5","number":"92","rarity":"Special Illustration Rare","types":["Darkness"],"hp":"210","artist":"kantaro","imageSmall":"https://images.pokemontcg.io/sv6pt5/92.png","imageLarge":"https://images.pokemontcg.io/sv6pt5/92_hires.png"},{"id":"sv6pt5-93","name":"Pecharunt ex","set":"Shrouded Fable","setId":"sv6pt5","number":"93","rarity":"Special Illustration Rare","types":["Darkness"],"hp":"190","artist":"kantaro","imageSmall":"https://images.pokemontcg.io/sv6pt5/93.png","imageLarge":"https://images.pokemontcg.io/sv6pt5/93_hires.png"},{"id":"sv6pt5-94","name":"Cassiopeia","set":"Shrouded Fable","setId":"sv6pt5","number":"94","rarity":"Special Illustration Rare","types":[],"hp":null,"artist":"burari","imageSmall":"https://images.pokemontcg.io/sv6pt5/94.png","imageLarge":"https://images.pokemontcg.io/sv6pt5/94_hires.png"},{"id":"sv6pt5-95","name":"Pecharunt ex","set":"Shrouded Fable","setId":"sv6pt5","number":"95","rarity":"Hyper Rare","types":["Darkness"],"hp":"190","artist":"aky CG Works","imageSmall":"https://images.pokemontcg.io/sv6pt5/95.png","imageLarge":"https://images.pokemontcg.io/sv6pt5/95_hires.png"},{"id":"sv6pt5-96","name":"Earthen Vessel","set":"Shrouded Fable","setId":"sv6pt5","number":"96","rarity":"Hyper Rare","types":[],"hp":null,"artist":"AYUMI ODASHIMA","imageSmall":"https://images.pokemontcg.io/sv6pt5/96.png","imageLarge":"https://images.pokemontcg.io/sv6pt5/96_hires.png"},{"id":"sv6pt5-97","name":"Powerglass","set":"Shrouded Fable","setId":"sv6pt5","number":"97","rarity":"Hyper Rare","types":[],"hp":null,"artist":"Studio Bora Inc.","imageSmall":"https://images.pokemontcg.io/sv6pt5/97.png","imageLarge":"https://images.pokemontcg.io/sv6pt5/97_hires.png"},{"id":"sv6pt5-98","name":"Basic Darkness Energy","set":"Shrouded Fable","setId":"sv6pt5","number":"98","rarity":"Hyper Rare","types":["Darkness"],"hp":null,"artist":null,"imageSmall":"https://images.pokemontcg.io/sv6pt5/98.png","imageLarge":"https://images.pokemontcg.io/sv6pt5/98_hires.png"},{"id":"sv6pt5-99","name":"Basic Metal Energy","set":"Shrouded Fable","setId":"sv6pt5","number":"99","rarity":"Hyper Rare","types":["Metal"],"hp":null,"artist":null,"imageSmall":"https://images.pokemontcg.io/sv6pt5/99.png","imageLarge":"https://images.pokemontcg.io/sv6pt5/99_hires.png"}]}